memry-0.1.0.data/scripts/memryd.exe
memry-0.1.0.dist-info/METADATA
memry-0.1.0.dist-info/WHEEL
memry-0.1.0.dist-info/licenses/LICENSE
memry/__init__.py
memry/__pycache__/__init__.cpython-311.pyc
memry/__pycache__/client.cpython-311.pyc
memry/__pycache__/exceptions.cpython-311.pyc
memry/__pycache__/server.cpython-311.pyc
memry/client.py
memry/exceptions.py
memry/server.py
memry-0.1.0.dist-info/RECORD
