Metadata-Version: 2.4
Name: memry
Version: 0.1.0
Classifier: License :: OSI Approved :: MIT License
Classifier: Programming Language :: Python
Classifier: Programming Language :: Python :: 3
Classifier: Programming Language :: Rust
Requires-Dist: pandas>=1.0
Requires-Dist: pyarrow>=10.0
License-File: LICENSE
Summary: Lightning-fast, in-memory, cross-process data store for Python
Author-email: Your Name <your@email.com>
Requires-Python: >=3.8
Project-URL: Homepage, https://github.com/your-username/memry
Project-URL: Repository, https://github.com/your-username/memry
